odoo8_addon_hw_telium_payment_terminal-8.0.0.1.2-nspkg.pth
odoo_addons/hw_telium_payment_terminal/README.rst
odoo_addons/hw_telium_payment_terminal/__init__.py
odoo_addons/hw_telium_payment_terminal/__openerp__.py
odoo_addons/hw_telium_payment_terminal/controllers/__init__.py
odoo_addons/hw_telium_payment_terminal/controllers/main.py
odoo_addons/hw_telium_payment_terminal/i18n/hw_telium_payment_terminal.pot
odoo_addons/hw_telium_payment_terminal/static/description/icon.png
odoo_addons/hw_telium_payment_terminal/test-scripts/telium-test.py
odoo8_addon_hw_telium_payment_terminal-8.0.0.1.2.dist-info/METADATA
odoo8_addon_hw_telium_payment_terminal-8.0.0.1.2.dist-info/WHEEL
odoo8_addon_hw_telium_payment_terminal-8.0.0.1.2.dist-info/namespace_packages.txt
odoo8_addon_hw_telium_payment_terminal-8.0.0.1.2.dist-info/top_level.txt
odoo8_addon_hw_telium_payment_terminal-8.0.0.1.2.dist-info/RECORD
